jade_helper/__init__.py
jade_helper/light_detector.py
jade_helper-0.0.6.dist-info/METADATA
jade_helper-0.0.6.dist-info/WHEEL
jade_helper-0.0.6.dist-info/top_level.txt
jade_helper-0.0.6.dist-info/RECORD
