Metadata-Version: 2.1
Name: jade-helper
Version: 0.0.6
Summary: Package creation test
Home-page: UNKNOWN
Author: Jade Perdereau
Author-email: jade.perdereau@free.fr
License: UNKNOWN
Platform: UNKNOWN
Classifier: Programming Language :: Python :: 3
Classifier: License :: OSI Approved :: MIT License
Classifier: Operating System :: OS Independent
Requires-Python: >=3.6
